mitama/__init__.py
mitama/_extra.py
mitama/app/__init__.py
mitama/app/app.py
mitama/app/builder.py
mitama/app/forms/__init__.py
mitama/app/forms/errors.py
mitama/app/forms/fields.py
mitama/app/hook.py
mitama/app/http/__init__.py
mitama/app/http/request.py
mitama/app/http/response.py
mitama/app/http/session.py
mitama/app/method.py
mitama/app/registry.py
mitama/app/router.py
mitama/app/static/favicon.ico
mitama/app/static/mitama-style.css
mitama/app/static/mitama-style.css.map
mitama/app/static/noimage_app.png
mitama/app/static/noimage_group.png
mitama/app/static/noimage_user.png
mitama/app/static/sw.js
mitama/app/templates/400.html
mitama/app/templates/401.html
mitama/app/templates/403.html
mitama/app/templates/404.html
mitama/app/templates/500.html
mitama/app/templates/502.html
mitama/app/templates/503.html
mitama/app/templates/base/error
mitama/app/templates/base/login
mitama/app/templates/base/plain
mitama/app/templates/footers.macro.html
mitama/app/templates/forms.macro.html
mitama/app/templates/headers.macro.html
mitama/app/templates/lists.macro.html
mitama/app/templates/navs.macro.html
mitama/app/templates/snippets.macro.html
mitama/commands.py
mitama/db/__init__.py
mitama/db/driver/__init__.py
mitama/db/driver/sqlite3.py
mitama/db/event.py
mitama/db/model.py
mitama/db/types.py
mitama/models/__init__.py
mitama/models/core_db.py
mitama/models/nodes.py
mitama/models/permissions.py
mitama/noimage.py
mitama/portal/__init__.py
mitama/portal/controller.py
mitama/portal/forms.py
mitama/portal/main.py
mitama/portal/middleware.py
mitama/portal/static/entrance-style.css
mitama/portal/static/entrance-style.css.map
mitama/portal/static/icon.png
mitama/portal/static/logo.svg
mitama/portal/static/mitama-style.css
mitama/portal/static/mitama-style.css.map
mitama/portal/static/mypage.svg
mitama/portal/static/noimage_team.svg
mitama/portal/static/noimage_user.svg
mitama/portal/static/settings.svg
mitama/portal/static/simplemde.min.css
mitama/portal/static/simplemde.min.js
mitama-4.6.20.dist-info/entry_points.txt
mitama-4.6.20.dist-info/LICENSE
mitama-4.6.20.dist-info/WHEEL
mitama-4.6.20.dist-info/METADATA
mitama-4.6.20.dist-info/RECORD
