Metadata-Version: 2.1
Name: mitama
Version: 4.6.20
Summary: 
License: MIT
Author: boke0
Author-email: speken00.tt@gmail.com
Requires-Python: >=3.6,<4.0
Classifier: License :: OSI Approved :: MIT License
Classifier: Programming Language :: Python :: 3
Classifier: Programming Language :: Python :: 3.6
Classifier: Programming Language :: Python :: 3.7
Classifier: Programming Language :: Python :: 3.8
Classifier: Programming Language :: Python :: 3.9
Requires-Dist: Jinja2 (>=2.11.3,<3.0.0)
Requires-Dist: Markdown (>=3.3.3,<4.0.0)
Requires-Dist: Pillow (>=8.1.0,<9.0.0)
Requires-Dist: PyJWT (>=2.0.1,<3.0.0)
Requires-Dist: SQLAlchemy (>=1.3.23,<2.0.0)
Requires-Dist: bcrypt (>=3.2.0,<4.0.0)
Requires-Dist: gevent (>=21.1.2,<22.0.0)
Requires-Dist: gevent-websocket (>=0.10.1,<0.11.0)
Requires-Dist: jinja-markdown (>=1.200630,<2.0)
Requires-Dist: pycryptodome (>=3.10.1,<4.0.0)
Requires-Dist: pysaml2 (>=6.5.1,<7.0.0)
Requires-Dist: python-magic (>=0.4.22,<0.5.0)
Requires-Dist: pywebpush (>=1.11.0,<2.0.0)
Requires-Dist: tzlocal (>=2.1,<3.0)
Requires-Dist: uWSGI (>=2.0.19,<3.0.0)
Requires-Dist: watchdog (>=2.0.1,<3.0.0)
